mol_dynamics-0.1.0.dist-info/METADATA
mol_dynamics-0.1.0.dist-info/WHEEL
mol_dynamics-0.1.0.dist-info/licenses/PYPI_LICENSE
mol_dynamics/__init__.py
mol_dynamics/mol_dynamics.abi3.so
mol_dynamics-0.1.0.dist-info/RECORD
