Metadata-Version: 2.4
Name: mol_dynamics
Version: 0.1.0
Classifier: Intended Audience :: Science/Research
Classifier: Topic :: Scientific/Engineering :: Bio-Informatics
Classifier: Programming Language :: Rust
Classifier: Programming Language :: Python :: Implementation :: CPython
Classifier: Programming Language :: Python :: Implementation :: PyPy
License-File: PYPI_LICENSE
Summary: Run GPU and SIMD-accelerated molecular dynamics simulations
Keywords: mol2,sdf,mmcif,amber,biology
Author-email: David O'Connor <the_alchemist@fastmail.com>
Requires-Python: >=3.10
Project-URL: homepage, https://github.com/David-OConnor/dynamics
Project-URL: repository, https://github.com/David-OConnor/dynamics
Project-URL: documentation, https://docs.rs/dynamics
